datasetCleaner/__init__.py
datasetCleaner-0.1.dist-info/LICENSE
datasetCleaner-0.1.dist-info/METADATA
datasetCleaner-0.1.dist-info/WHEEL
datasetCleaner-0.1.dist-info/top_level.txt
datasetCleaner-0.1.dist-info/RECORD
