Metadata-Version: 2.1
Name: datasetCleaner
Version: 0.1
Summary: A dataset cleaner for pictures
Home-page: https://github.com/felop/datasetCleaner
Author: Félix Lopez
Author-email: feloxlopez05@gmail.com
License: UNKNOWN
Platform: UNKNOWN
Classifier: Programming Language :: Python :: 3
Classifier: License :: OSI Approved :: MIT License
Classifier: Operating System :: OS Independent
